ysights/__init__.py
ysights/algorithms/__init__.py
ysights/algorithms/paradox.py
ysights/algorithms/profiles.py
ysights/algorithms/recommenders.py
ysights/algorithms/topics.py
ysights/models/Agents.py
ysights/models/Posts.py
ysights/models/YDataHandler.py
ysights/models/__init__.py
ysights/test/__init__.py
ysights/test/test_algos.py
ysights/test/test_datahandler.py
ysights/test/test_postgresql_integration.py
ysights/test/test_postgresql_support.py
ysights/test/test_recommenter.py
ysights/test/test_topic.py
ysights/test/test_viz.py
ysights/viz/__init__.py
ysights/viz/global_trends.py
ysights/viz/paradox_viz.py
ysights/viz/profiles_viz.py
ysights/viz/recommendations.py
ysights/viz/topics_viz.py
ysights-0.1.0.dist-info/licenses/LICENSE
ysights-0.1.0.dist-info/METADATA
ysights-0.1.0.dist-info/WHEEL
ysights-0.1.0.dist-info/top_level.txt
ysights-0.1.0.dist-info/RECORD
