Metadata-Version: 2.4
Name: ysights
Version: 0.1.0
Summary: ySights - Extract insights from YSocial simulations
Home-page: https://github.com/YSocialTwin/ysights
Author: Giulio Rossetti
Author-email: Giulio Rossetti <giulio.rossetti@gmail.com>
License: GPL-3.0
Project-URL: Homepage, https://github.com/YSocialTwin/ysights
Project-URL: Documentation, https://ysights.readthedocs.io
Project-URL: Repository, https://github.com/YSocialTwin/ysights
Project-URL: Issues, https://github.com/YSocialTwin/ysights/issues
Keywords: community-discovery,node-clustering,edge-clustering,complex-networks,social-simulation
Classifier: Development Status :: 4 - Beta
Classifier: Intended Audience :: Developers
Classifier: Intended Audience :: Science/Research
Classifier: Topic :: Software Development :: Build Tools
Classifier: Topic :: Scientific/Engineering :: Information Analysis
Classifier: License :: OSI Approved :: GNU General Public License v3 (GPLv3)
Classifier: Operating System :: POSIX
Classifier: Operating System :: MacOS
Classifier: Programming Language :: Python :: 3
Classifier: Programming Language :: Python :: 3.9
Classifier: Programming Language :: Python :: 3.10
Classifier: Programming Language :: Python :: 3.11
Classifier: Programming Language :: Python :: 3.12
Requires-Python: >=3.9
License-File: LICENSE
Requires-Dist: networkx
Requires-Dist: matplotlib
Requires-Dist: numpy
Requires-Dist: scipy
Requires-Dist: seaborn
Requires-Dist: plotly
Requires-Dist: scikit-learn
Requires-Dist: pandas
Requires-Dist: tqdm
Provides-Extra: postgresql
Requires-Dist: psycopg2-binary; extra == "postgresql"
Dynamic: author
Dynamic: home-page
Dynamic: license-file
